{
  "placeholderImages": [
    {
      "id": "logo",
      "description": "Logo Ndara Afrique",
      "imageUrl": "https://ndara-assets.b-cdn.net/logo.png",
      "imageHint": "logo brand"
    },
    {
      "id": "devweb",
      "description": "Introduction au Développement Web",
      "imageUrl": "https://images.unsplash.com/photo-1608742213509-815b97c30b36?crop=entropy&cs=tinysrgb&fit=max&fm=jpg&q=80&w=1080",
      "imageHint": "code screen"
    },
    {
      "id": "marketing",
      "description": "Les Fondamentaux du Marketing Digital",
      "imageUrl": "https://images.unsplash.com/photo-1722172597269-d911054badb9?crop=entropy&cs=tinysrgb&fit=max&fm=jpg&q=80&w=1080",
      "imageHint": "social media chart"
    },
    {
      "id": "ai",
      "description": "Initiation à l'Intelligence Artificielle",
      "imageUrl": "https://images.unsplash.com/photo-1738082956254-1dd63ad1db71?crop=entropy&cs=tinysrgb&fit=max&fm=jpg&q=80&w=1080",
      "imageHint": "abstract network"
    },
    {
      "id": "browse-courses",
      "description": "A grid view of course cards on a screen.",
      "imageUrl": "https://ndara-assets.b-cdn.net/assets/browse-courses.jpg",
      "imageHint": "course grid"
    },
    {
      "id": "mobile-payment",
      "description": "A person making a payment on a smartphone.",
      "imageUrl": "https://ndara-assets.b-cdn.net/assets/mobile-payment.jpg",
      "imageHint": "mobile payment"
    },
    {
      "id": "certificate",
      "description": "A digital certificate of completion on a screen.",
      "imageUrl": "https://ndara-assets.b-cdn.net/assets/certificate.jpg",
      "imageHint": "certificate screen"
    },
    {
      "id": "payment-security",
      "description": "Abstract image of a padlock on a screen with code, representing digital security.",
      "imageUrl": "https://ndara-assets.b-cdn.net/assets/security.jpg",
      "imageHint": "digital security"
    },
    {
      "id": "final-cta-bg",
      "description": "Students collaborating and looking towards the future.",
      "imageUrl": "https://ndara-assets.b-cdn.net/assets/students-collaboration.jpg",
      "imageHint": "students learning"
    }
  ]
}